LICENSE
MANIFEST.in
README.rst
setup.py
adfav/__init__.py
adfav/admin.py
adfav/fake_field.py
adfav/models.py
adfav/tests.py
adfav/urls.py
adfav/utils.py
adfav/views.py
django_admin_favorite.egg-info/PKG-INFO
django_admin_favorite.egg-info/SOURCES.txt
django_admin_favorite.egg-info/dependency_links.txt
django_admin_favorite.egg-info/requires.txt
django_admin_favorite.egg-info/top_level.txt