Metadata-Version: 1.1
Name: django-admin-favorite
Version: 0.1.1
Summary: A simple Django app to add items to favorite in admin interface.
Home-page: https://bitbucket.org/freylis/django-admin-favorite
Author: Mike Volkov
Author-email: freylis2@gmail.com
License: MIT License
Platform: UNKNOWN
Classifier: Environment :: Web Environment
Classifier: Framework :: Django
Classifier: Intended Audience :: Developers
Classifier: License :: OSI Approved :: MIT License
Classifier: Operating System :: OS Independent
Classifier: Programming Language :: Python
Classifier: Programming Language :: Python :: 2.6
Classifier: Programming Language :: Python :: 2.7
Classifier: Topic :: Internet :: WWW/HTTP
Classifier: Topic :: Internet :: WWW/HTTP :: Dynamic Content
